{
  "timestamp": "2025-10-27T14:15:08.299Z",
  "summary": {
    "total_components": 6,
    "components_validated": 6,
    "dependencies_installed": true,
    "build_successful": true,
    "tests_run": true
  },
  "components": [
    {
      "name": "AdvancedDashboardIntegrated",
      "file": "AdvancedDashboardIntegrated.tsx",
      "status": "validated",
      "features": 5,
      "dependencies": 2
    },
    {
      "name": "SEOContentGenerator",
      "file": "SEOContentGenerator.tsx",
      "status": "validated",
      "features": 3,
      "dependencies": 2
    },
    {
      "name": "BlockchainRewards",
      "file": "BlockchainRewards.tsx",
      "status": "validated",
      "features": 4,
      "dependencies": 2
    },
    {
      "name": "MetaversePortal",
      "file": "MetaversePortal.tsx",
      "status": "validated",
      "features": 4,
      "dependencies": 2
    },
    {
      "name": "AutomationWorkflows",
      "file": "AutomationWorkflows.tsx",
      "status": "validated",
      "features": 4,
      "dependencies": 2
    },
    {
      "name": "TensorFlowAdmin",
      "file": "TensorFlowAdmin.tsx",
      "status": "validated",
      "features": 4,
      "dependencies": 2
    }
  ],
  "workflows_created": [
    "seo-workflow.json",
    "mining-workflow.json"
  ],
  "monitoring_enabled": true,
  "documentation_generated": true,
  "next_steps": [
    "Run npm start to launch the development server",
    "Visit http://localhost:3000 to access the dashboard",
    "Explore each component tab for advanced features",
    "Configure automation workflows as needed",
    "Monitor system performance through the dashboard"
  ]
}